MANIFEST.in
README.rst
setup.py
templated_emails/__init__.py
templated_emails/models.py
templated_emails/parse_util.py
templated_emails/tests.py
templated_emails/urls.py
templated_emails/utils.py
templated_emails/views.py
templated_emails.egg-info/PKG-INFO
templated_emails.egg-info/SOURCES.txt
templated_emails.egg-info/dependency_links.txt
templated_emails.egg-info/requires.txt
templated_emails.egg-info/top_level.txt
templated_emails/templates/templated_emails/directory.html
templated_emails/templates/templated_emails/index.html
templated_emails/templates/templated_emails/view.html
templated_emails/templatetags/__init__.py
templated_emails/templatetags/templated_email_tags.py