Metadata-Version: 1.1
Name: templated-emails
Version: 0.6.9
Summary: Like django-notifications, but just for sending plain emails. Written because it is annoying to fork other apps just to make an email into an HTML email
Home-page: https://github.com/philippWassibauer/templated-emails
Author: Philipp Wassibauer
Author-email: phil@gidsy.com
License: MIT License
Platform: UNKNOWN
Classifier: Development Status :: 4 - Beta
Classifier: Environment :: Web Environment
Classifier: Framework :: Django
Classifier: Intended Audience :: Developers
Classifier: License :: OSI Approved :: MIT License
Classifier: Topic :: Internet :: WWW/HTTP :: Dynamic Content
